structify_net/__init__.py
structify_net/scoring.py
structify_net/structureClasses.py
structify_net/transform.py
structify_net/viz.py
structify_net/zoo.py
structify_net/__pycache__/__init__.cpython-311.pyc
structify_net/__pycache__/__init__.cpython-38.pyc
structify_net/__pycache__/scoring.cpython-311.pyc
structify_net/__pycache__/scoring.cpython-38.pyc
structify_net/__pycache__/structureClasses.cpython-311.pyc
structify_net/__pycache__/structureClasses.cpython-38.pyc
structify_net/__pycache__/test.cpython-311.pyc
structify_net/__pycache__/transform.cpython-311.pyc
structify_net/__pycache__/transform.cpython-38.pyc
structify_net/__pycache__/viz.cpython-311.pyc
structify_net/__pycache__/viz.cpython-38.pyc
structify_net/__pycache__/zoo.cpython-311.pyc
structify_net/__pycache__/zoo.cpython-38.pyc
structify_net-0.9.50.post0.dist-info/LICENSE
structify_net-0.9.50.post0.dist-info/METADATA
structify_net-0.9.50.post0.dist-info/WHEEL
structify_net-0.9.50.post0.dist-info/top_level.txt
structify_net-0.9.50.post0.dist-info/RECORD
