Metadata-Version: 2.1
Name: structify-net
Version: 0.9.50.post0
Summary: Network Generation with controlled structure
Author-email: Remy Cazabet <emy.cazabet@gmail.com>
License: MIT
Project-URL: Documentation, http://structify-net.readthedocs.io
Project-URL: Source, https://github.com/Yquetzal/structify_net
Keywords: network-science,community-detection
License-File: LICENSE
Requires-Dist: networkx
Requires-Dist: pandas
Requires-Dist: matplotlib
Requires-Dist: seaborn
Requires-Dist: numpy
Requires-Dist: scipy
Requires-Dist: tqdm
Requires-Dist: mock
Requires-Dist: perlin-noise
